ros2_utils/__init__.py
ros2_utils/callbacks.py
ros2_utils-0.0.1.dist-info/LICENCE
ros2_utils-0.0.1.dist-info/METADATA
ros2_utils-0.0.1.dist-info/WHEEL
ros2_utils-0.0.1.dist-info/top_level.txt
ros2_utils-0.0.1.dist-info/RECORD
