Metadata-Version: 2.1
Name: ros2-utils
Version: 0.0.1
Summary: ROS2 utils.
Home-page: https://github.com/pypa/ros2_utils
Author: Michael Ramos
Author-email: mike.ramos58@gmail.com
License: UNKNOWN
Platform: UNKNOWN
Classifier: Programming Language :: Python :: 3
Classifier: License :: OSI Approved :: MIT License
Classifier: Operating System :: OS Independent
